Metadata-Version: 1.0
Name: fz-distributions
Version: 0.1
Summary: Gaussian and Binomial distributions
Home-page: UNKNOWN
Author: Federico Zimmermann
Author-email: fedezimm@gmail.com
License: UNKNOWN
Platform: UNKNOWN
